portray/__init__.py
portray/_version.py
portray/api.py
portray/cli.py
portray/config.py
portray/exceptions.py
portray/logo.py
portray/render.py
portray/mkdocs_templates/partials/footer.html
tmp_fat_portray-1.8.0.dist-info/METADATA
tmp_fat_portray-1.8.0.dist-info/WHEEL
tmp_fat_portray-1.8.0.dist-info/entry_points.txt
tmp_fat_portray-1.8.0.dist-info/licenses/LICENSE
tmp_fat_portray-1.8.0.dist-info/RECORD
