Metadata-Version: 2.1
Name: tmp_fat_portray
Version: 1.8.0
Summary: Your Project with Great Documentation
Author-email: Timothy Crosley <timothy.crosley@gmail.com>
License-Expression: MIT
License-File: LICENSE
Requires-Python: >=3.8
Requires-Dist: click>=8.1
Requires-Dist: gitpython>=3.0
Requires-Dist: livereload>=2.6.3
Requires-Dist: mkdocs-material>=7.0
Requires-Dist: mkdocs<1.4.0,>=1.3.0
Requires-Dist: pymdown-extensions>=7.0
Requires-Dist: tmp-fat-pdocs>=v1.2.0
Requires-Dist: toml>=0.10.0
Requires-Dist: yaspin<3,>=0.15.0
Provides-Extra: dev
Requires-Dist: bandit>=1.6; extra == 'dev'
Requires-Dist: black>1.0.0; extra == 'dev'
Requires-Dist: cruft>=2.2; extra == 'dev'
Requires-Dist: hypothesis-auto; extra == 'dev'
Requires-Dist: ipython>=7.7; extra == 'dev'
Requires-Dist: mypy>0.730.0; extra == 'dev'
Requires-Dist: pprofile>=2.0; extra == 'dev'
Requires-Dist: pytest-cov>=2.7; extra == 'dev'
Requires-Dist: pytest-mock>=1.10; extra == 'dev'
Requires-Dist: pytest>=5.1; extra == 'dev'
Requires-Dist: ruff>=0.0.191; extra == 'dev'
Requires-Dist: safety>=1.8; extra == 'dev'
Requires-Dist: types-toml>0.0; extra == 'dev'
